zapy/__about__.py
zapy/__init__.py
zapy/__init__.pyi
zapy/cli.py
zapy/api/__init__.py
zapy/api/bootstrapper.py
zapy/api/connection.py
zapy/api/exceptions.py
zapy/api/models.py
zapy/api/server.py
zapy/api/deps/__init__.py
zapy/api/deps/socketio.py
zapy/api/v1/__init__.py
zapy/api/v1/api_requests.py
zapy/api/v1/api_server.py
zapy/api/v1/api_store.py
zapy/base/__init__.py
zapy/base/auto.py
zapy/base/exceptions.py
zapy/base/models.py
zapy/requests/__init__.py
zapy/requests/context.py
zapy/requests/converter.py
zapy/requests/exceptions.py
zapy/requests/file_loader.py
zapy/requests/hooks.py
zapy/requests/models.py
zapy/requests/requester.py
zapy/store/__init__.py
zapy/store/attr.py
zapy/store/context.py
zapy/store/manager.py
zapy/templating/__init__.py
zapy/templating/eval.py
zapy/templating/templating.py
zapy/templating/traceback.py
zapy/test/__init__.py
zapy/test/assertion.py
zapy/test/models.py
zapy/test/test_case.py
zapy/test/test_runner.py
zapy/utils/__init__.py
zapy/utils/functools.py
zapy/utils/module.py
zapy/utils/singleton.py
zapy_sdk-0.0.1a2.dist-info/METADATA
zapy_sdk-0.0.1a2.dist-info/WHEEL
zapy_sdk-0.0.1a2.dist-info/entry_points.txt
zapy_sdk-0.0.1a2.dist-info/licenses/LICENSE.txt
zapy_sdk-0.0.1a2.dist-info/RECORD
