Metadata-Version: 2.1
Name: zapy-sdk
Version: 0.0.1a2
Summary: Zapy SDK for Zapy REST client
Project-URL: Homepage, https://zapy.dev
Project-URL: Documentation, https://docs.zapy.dev
Project-URL: Issues, https://github.com/ZapyLabs/zapy-sdk/issues
Project-URL: Source, https://github.com/ZapyLabs/zapy-sdk
Author: zapy.dev
License: Copyright (C) 2023-present zapy.dev
License-File: LICENSE.txt
Classifier: Intended Audience :: Developers
Classifier: Programming Language :: Python :: 3 :: Only
Classifier: Programming Language :: Python :: 3.11
Classifier: Programming Language :: Python :: 3.12
Requires-Python: >=3.11
Requires-Dist: fastapi>0.95.0
Requires-Dist: httpx==0.*
Requires-Dist: jinja2==3.*
Requires-Dist: magicattr
Requires-Dist: pydantic==2.*
Requires-Dist: python-socketio[asyncio-client]
Requires-Dist: uvicorn==0.*
Requires-Dist: wrapt==1.*
